{
  "name": "Dale Larson",
  "age": 37,
  "address": {
    "street": "Saki Path",
    "city": "Pogpaac",
    "state": "WY",
    "zip": "51945"
  },
  "contact": {
    "phone": "(305) 890-6959",
    "servicePhone": "800435982"
  },
  "birthday": "1964-12-08T02:37:17.388Z",
  "ip": "26.79.46.86",
  "foo": "bar",
  "profile": {
    "about": "Cu hivwim giviloz be vu go ti ug hir non zotuj malovoz. Itiemja negdebab pibek nog sipefra hocki monin je va anew ajcen unainas los mipudat unagi sis siazora. Gepfob lu aza lenzi zaza lulmez nazesa vusvaz lafefso awweru wilik ej usa. Mapeh rutsoznof nifjijus guher okigunuf encupo jah ni us fah ralwihjul girnot ijevos hu zu go. Gisok ru buc ki mut vi daruvmic mezud taji fihloj sicefke isem halbezi hezeude gela tiwupek lil. Pibne cozjore naci seacfi hefez cam sasza calaj ika uho ihusuari rabimron umias we lattucec. Le simivoke verug bukzapdip nol temavwa efo suza ju pihwibem kir pu ilacekge tuwve jubesral hi.",
    "bio": "Do si bi ima nuw pezakev zi afosomahu supucdo ifuiwu ope bulat rodgid otod vadeb ka po wu. Odaegru ucudow laapo kahemi eg nis hoza jomozaj roged ojzo joeno mowunfos. Fuc opzi ciebi miomataf bekej igireuwo ceruta enakocgab em vezepsej zitpehjeg gasieh larjafpu. Jowi notet uj nes ja gompo vezjecjov lat tongozta wilpukce sid sasgubet adiaze hegacu dunel. Muostij maizibit la he wegi kebwema zuzakzoj eta no cijuraw dehuk buc."
  },
  "apiKey": "45763a9a96c06ee3a278581b1a1ea92c269dd464f2ab72ac187790e5547c9ac1",
  "currency": {
    "code": "LBP",
    "name": "Lebanon Pound"
  }
}